LICENSE.txt
MANIFEST.in
README.txt
setup.py
pcart_1c_soap_api.egg-info/PKG-INFO
pcart_1c_soap_api.egg-info/SOURCES.txt
pcart_1c_soap_api.egg-info/dependency_links.txt
pcart_1c_soap_api.egg-info/not-zip-safe
pcart_1c_soap_api.egg-info/requires.txt
pcart_1c_soap_api.egg-info/top_level.txt
soap_1c_api/__init__.py
soap_1c_api/admin.py
soap_1c_api/apps.py
soap_1c_api/jobs.py
soap_1c_api/lxml_import.py
soap_1c_api/models.py
soap_1c_api/py2xml.py
soap_1c_api/tasks.py
soap_1c_api/tests.py
soap_1c_api/urls.py
soap_1c_api/webservice.py
soap_1c_api/locale/ru/LC_MESSAGES/django.mo
soap_1c_api/locale/ru/LC_MESSAGES/django.po
soap_1c_api/locale/uk/LC_MESSAGES/django.mo
soap_1c_api/locale/uk/LC_MESSAGES/django.po
soap_1c_api/management/__init__.py
soap_1c_api/management/commands/__init__.py
soap_1c_api/management/commands/load_product_images.py
soap_1c_api/migrations/0001_initial.py
soap_1c_api/migrations/0002_auto_20170308_1305.py
soap_1c_api/migrations/0003_auto_20170308_1457.py
soap_1c_api/migrations/0004_auto_20170308_1514.py
soap_1c_api/migrations/0005_auto_20170309_1142.py
soap_1c_api/migrations/__init__.py
soap_server/__init__.py
soap_server/models.py
soap_server/soap.py
soap_server/urls.py
soap_server/utils.py
soap_server/webservice.py
soap_server/wsgi.py
soap_server/tests/__init__.py
soap_server/tests/wsgi.py
soaplib/__init__.py
soaplib/core/__init__.py
soaplib/core/_base.py
soaplib/core/mime.py
soaplib/core/namespaces.py
soaplib/core/service.py
soaplib/core/styles.py
soaplib/core/wsdl.py
soaplib/core/zope2.py
soaplib/core/model/__init__.py
soaplib/core/model/base.py
soaplib/core/model/binary.py
soaplib/core/model/clazz.py
soaplib/core/model/enum.py
soaplib/core/model/exception.py
soaplib/core/model/primitive.py
soaplib/core/model/table.py
soaplib/core/server/__init__.py
soaplib/core/server/_base.py
soaplib/core/server/wsgi.py
soaplib/core/server/zeromq.py
soaplib/core/test/__init__.py
soaplib/core/test/test_service.py
soaplib/core/test/test_soap.py
soaplib/core/test/test_xml_output.py
soaplib/core/test/test_xsd_gen.py
soaplib/core/test/interop/__init__.py
soaplib/core/test/interop/test_suds.py
soaplib/core/test/interop/test_wsi.py
soaplib/core/test/interop/server/__init__.py
